pypas/__init__.py
pypas/main.py
pypas/settings.py
pypas/lib/auth.py
pypas/lib/config.py
pypas/lib/console.py
pypas/lib/decorators.py
pypas/lib/exercise.py
pypas/lib/monads.py
pypas/lib/network.py
pypas/lib/sysutils.py
pypas_cli-0.5.5.dist-info/licenses/LICENSE
pypas_cli-0.5.5.dist-info/METADATA
pypas_cli-0.5.5.dist-info/WHEEL
pypas_cli-0.5.5.dist-info/entry_points.txt
pypas_cli-0.5.5.dist-info/top_level.txt
pypas_cli-0.5.5.dist-info/RECORD
