Metadata-Version: 2.4
Name: pypas-cli
Version: 0.5.5
Summary: Python Practical Assignments
Author-email: Sergio Delgado Quintero <sdelquin@gmail.com>
Maintainer-email: Sergio Delgado Quintero <sdelquin@gmail.com>
Project-URL: homepage, https://pypas.es
Project-URL: repository, https://github.com/sdelquin/pypas-cli
Project-URL: issues, https://github.com/sdelquin/pypas-cli/issues
Classifier: Programming Language :: Python :: 3
Classifier: Operating System :: OS Independent
Requires-Python: >=3.10
License-File: LICENSE
Requires-Dist: pathspec>=0.12.1
Requires-Dist: prettyconf>=2.3.0
Requires-Dist: pytest>=8.4.1
Requires-Dist: pytest-dependency>=0.6.0
Requires-Dist: requests>=2.32.4
Requires-Dist: requests-toolbelt>=1.0.0
Requires-Dist: rich>=14.1.0
Requires-Dist: toml>=0.10.2
Requires-Dist: typer>=0.16.0
Dynamic: license-file
